applications/README.md
applications/commercial_roadmaps/README.md
applications/commercial_roadmaps/quantum_technology_roadmap.md
applications/patent_disclosures/README.md
applications/patent_disclosures/eqfe_core_technology.md
build/lib/applications/README.md
build/lib/applications/commercial_roadmaps/README.md
build/lib/applications/commercial_roadmaps/quantum_technology_roadmap.md
build/lib/applications/patent_disclosures/README.md
build/lib/applications/patent_disclosures/eqfe_core_technology.md
build/lib/collaboration/README.md
build/lib/collaboration/data_sharing_protocols.md
build/lib/collaboration/publication_guidelines.md
build/lib/collaboration/research_partnership_guide.md
build/lib/complex_systems/emergence_modeling.py
build/lib/complex_systems/multi_scale_simulator.py
build/lib/complex_systems/information_processing/__init__.py
build/lib/complex_systems/measurement_protocols/__init__.py
build/lib/docs/CITATIONS.md
build/lib/docs/README.md
build/lib/docs/_config.yml
build/lib/docs/api_reference.md
build/lib/docs/computational_tools.md
build/lib/docs/evolution_from_cfh.md
build/lib/docs/experimental_validation.md
build/lib/docs/getting_started.md
build/lib/docs/index.md
build/lib/docs/multi_scale_framework.md
build/lib/docs/project_roadmap.md
build/lib/docs/publications.md
build/lib/docs/revolutionary_findings.md
build/lib/docs/theory.md
build/lib/docs/website_improvements.md
build/lib/docs/assets/images/webp-versions.md
build/lib/docs/theory/amplification_law_derivation.md
build/lib/docs/theory/conceptual_clarifications.md
build/lib/docs/theory/detailed_amplification_derivation.md
build/lib/docs/theory/falsification_framework.md
build/lib/docs/theory/theoretical_enhancement_plan.md
build/lib/docs/theory/tsirelson_bound_proof.md
build/lib/docs/visualization-assets/README.md
build/lib/docs/visualization-assets/amplification_mechanism.md
build/lib/docs/visualization-assets/field_correlation_dynamics.md
build/lib/docs/visualization-assets/index.md
eqfe-0.1.0.dist-info/licenses/LICENSE
eqfe-0.1.0.dist-info/METADATA
eqfe-0.1.0.dist-info/WHEEL
eqfe-0.1.0.dist-info/top_level.txt
eqfe-0.1.0.dist-info/RECORD
