Metadata-Version: 2.4
Name: eqfe
Version: 0.1.0
Summary: Environmental Quantum Field Effects (EQFE): Rigorous framework for modeling, simulation, and analysis of environmental quantum field effects in natural and engineered systems.
Home-page: https://github.com/pelicansperspective/Environmental-Quantum-Field-Effects
Author: EQFE Research Team
Author-email: Justin Todd <justin@pelicansperspective.com>
License: MIT License
Project-URL: Homepage, https://github.com/justin-todd/Environmental-Quantum-Field-Effects
Project-URL: Documentation, https://pelicansperspective.github.io/Environmental-Quantum-Field-Effects/
Project-URL: Source, https://github.com/justin-todd/Environmental-Quantum-Field-Effects
Project-URL: Issues, https://github.com/justin-todd/Environmental-Quantum-Field-Effects/issues
Keywords: quantum,field theory,environmental,simulation,physics,biology,quantum information
Classifier: Programming Language :: Python :: 3
Classifier: License :: OSI Approved :: MIT License
Classifier: Operating System :: OS Independent
Classifier: Intended Audience :: Science/Research
Classifier: Topic :: Scientific/Engineering :: Physics
Classifier: Topic :: Scientific/Engineering :: Information Analysis
Requires-Python: >=3.8
License-File: LICENSE
Requires-Dist: numpy>=1.21.0
Requires-Dist: scipy>=1.7.0
Requires-Dist: matplotlib>=3.4.0
Requires-Dist: pandas>=1.3.0
Requires-Dist: qutip>=4.6.0
Requires-Dist: sympy>=1.8.0
Requires-Dist: seaborn>=0.11.0
Requires-Dist: plotly>=5.0.0
Requires-Dist: jupyter>=1.0.0
Requires-Dist: scikit-learn>=1.0.0
Requires-Dist: statsmodels>=0.12.0
Requires-Dist: pytest>=6.2.0
Requires-Dist: pytest-cov>=2.12.0
Requires-Dist: hypothesis>=6.14.0
Requires-Dist: sphinx>=4.0.0
Requires-Dist: sphinx-rtd-theme>=0.5.0
Requires-Dist: nbsphinx>=0.8.0
Requires-Dist: black>=21.0.0
Requires-Dist: flake8>=3.9.0
Requires-Dist: isort>=5.9.0
Requires-Dist: mypy>=0.910
Dynamic: author
Dynamic: home-page
Dynamic: license-file
Dynamic: requires-python
